[
  {
    "symbol": "SNOW",
    "price": 136.22999572753906,
    "price_1mo_ago": 178.66000366210938,
    "change_percent": -23.75,
    "market_cap": 47094710272,
    "company_name": "Snowflake Inc.",
    "sector": "Technology",
    "industry": "Software - Application"
  },
  {
    "symbol": "NKE",
    "price": 43.7599983215332,
    "price_1mo_ago": 53.97999954223633,
    "change_percent": -18.93,
    "market_cap": 64803614720,
    "company_name": "NIKE, Inc.",
    "sector": "Consumer Cyclical",
    "industry": "Footwear & Accessories"
  },
  {
    "symbol": "OKTA",
    "price": 64.83000183105469,
    "price_1mo_ago": 79.16000366210938,
    "change_percent": -18.1,
    "market_cap": 11489836032,
    "company_name": "Okta, Inc.",
    "sector": "Technology",
    "industry": "Software - Infrastructure"
  },
  {
    "symbol": "INTU",
    "price": 369.67999267578125,
    "price_1mo_ago": 438.6045837402344,
    "change_percent": -15.71,
    "market_cap": 102872358912,
    "company_name": "Intuit Inc.",
    "sector": "Technology",
    "industry": "Software - Application"
  },
  {
    "symbol": "NET",
    "price": 180.3800048828125,
    "price_1mo_ago": 212.4499969482422,
    "change_percent": -15.1,
    "market_cap": 63490207744,
    "company_name": "Cloudflare, Inc.",
    "sector": "Technology",
    "industry": "Software - Infrastructure"
  },
  {
    "symbol": "TMUS",
    "price": 189.47000122070312,
    "price_1mo_ago": 217.38999938964844,
    "change_percent": -12.84,
    "market_cap": 211923451904,
    "company_name": "T-Mobile US, Inc.",
    "sector": "Communication Services",
    "industry": "Telecom Services"
  },
  {
    "symbol": "VZ",
    "price": 45.1349983215332,
    "price_1mo_ago": 50.618656158447266,
    "change_percent": -10.83,
    "market_cap": 190365171712,
    "company_name": "Verizon Communications Inc.",
    "sector": "Communication Services",
    "industry": "Telecom Services"
  },
  {
    "symbol": "DDOG",
    "price": 111.30999755859375,
    "price_1mo_ago": 124.5199966430664,
    "change_percent": -10.61,
    "market_cap": 39387189248,
    "company_name": "Datadog, Inc.",
    "sector": "Technology",
    "industry": "Software - Application"
  }
]