[
  {
    "symbol": "AZO",
    "price": 3020.949951171875,
    "price_1mo_ago": 3704.030029296875,
    "change_percent": -18.44,
    "market_cap": 49449930752,
    "company_name": "AutoZone, Inc.",
    "sector": "Consumer Cyclical",
    "industry": "Auto Parts"
  },
  {
    "symbol": "RBLX",
    "price": 47.0,
    "price_1mo_ago": 55.2599983215332,
    "change_percent": -14.95,
    "market_cap": 33651001344,
    "company_name": "Roblox Corporation",
    "sector": "Communication Services",
    "industry": "Electronic Gaming & Multimedia"
  },
  {
    "symbol": "REGN",
    "price": 600.6599731445312,
    "price_1mo_ago": 706.0054931640625,
    "change_percent": -14.92,
    "market_cap": 62972608512,
    "company_name": "Regeneron Pharmaceuticals, Inc.",
    "sector": "Healthcare",
    "industry": "Biotechnology"
  },
  {
    "symbol": "NEE",
    "price": 83.66000366210938,
    "price_1mo_ago": 97.87999725341797,
    "change_percent": -14.53,
    "market_cap": 174481752064,
    "company_name": "NextEra Energy, Inc.",
    "sector": "Utilities",
    "industry": "Utilities - Regulated Electric"
  },
  {
    "symbol": "CHTR",
    "price": 142.60000610351562,
    "price_1mo_ago": 165.1699981689453,
    "change_percent": -13.66,
    "market_cap": 20132036608,
    "company_name": "Charter Communications, Inc.",
    "sector": "Communication Services",
    "industry": "Telecom Services"
  },
  {
    "symbol": "DOW",
    "price": 34.689998626708984,
    "price_1mo_ago": 40.08242416381836,
    "change_percent": -13.45,
    "market_cap": 25002520576,
    "company_name": "Dow Inc.",
    "sector": "Basic Materials",
    "industry": "Chemicals"
  },
  {
    "symbol": "LOW",
    "price": 207.6999969482422,
    "price_1mo_ago": 238.7899932861328,
    "change_percent": -13.02,
    "market_cap": 116458856448,
    "company_name": "Lowe's Companies, Inc.",
    "sector": "Consumer Cyclical",
    "industry": "Home Improvement Retail"
  },
  {
    "symbol": "ALB",
    "price": 171.1300048828125,
    "price_1mo_ago": 196.6999969482422,
    "change_percent": -13.0,
    "market_cap": 20182157312,
    "company_name": "Albemarle Corporation",
    "sector": "Basic Materials",
    "industry": "Specialty Chemicals"
  },
  {
    "symbol": "WMT",
    "price": 114.5999984741211,
    "price_1mo_ago": 131.67869567871094,
    "change_percent": -12.97,
    "market_cap": 913475502080,
    "company_name": "Walmart Inc.",
    "sector": "Consumer Defensive",
    "industry": "Discount Stores"
  },
  {
    "symbol": "PEP",
    "price": 141.52000427246094,
    "price_1mo_ago": 158.49000549316406,
    "change_percent": -10.71,
    "market_cap": 193449492480,
    "company_name": "PepsiCo, Inc.",
    "sector": "Consumer Defensive",
    "industry": "Beverages - Non-Alcoholic"
  }
]